not_again_ai/__init__.py
not_again_ai/py.typed
not_again_ai/base/__init__.py
not_again_ai/base/file_system.py
not_again_ai/base/parallel.py
not_again_ai/data/__init__.py
not_again_ai/data/brave_search_api.py
not_again_ai/data/web.py
not_again_ai/llm/__init__.py
not_again_ai/llm/chat_completion/__init__.py
not_again_ai/llm/chat_completion/interface.py
not_again_ai/llm/chat_completion/types.py
not_again_ai/llm/chat_completion/providers/__init__.py
not_again_ai/llm/chat_completion/providers/anthropic_api.py
not_again_ai/llm/chat_completion/providers/gemini_api.py
not_again_ai/llm/chat_completion/providers/ollama_api.py
not_again_ai/llm/chat_completion/providers/openai_api.py
not_again_ai/llm/embedding/__init__.py
not_again_ai/llm/embedding/interface.py
not_again_ai/llm/embedding/types.py
not_again_ai/llm/embedding/providers/__init__.py
not_again_ai/llm/embedding/providers/ollama_api.py
not_again_ai/llm/embedding/providers/openai_api.py
not_again_ai/llm/image_gen/__init__.py
not_again_ai/llm/image_gen/interface.py
not_again_ai/llm/image_gen/types.py
not_again_ai/llm/image_gen/providers/__init__.py
not_again_ai/llm/image_gen/providers/openai_api.py
not_again_ai/llm/prompting/__init__.py
not_again_ai/llm/prompting/compile_prompt.py
not_again_ai/llm/prompting/interface.py
not_again_ai/llm/prompting/types.py
not_again_ai/llm/prompting/providers/__init__.py
not_again_ai/llm/prompting/providers/openai_tiktoken.py
not_again_ai/statistics/__init__.py
not_again_ai/statistics/dependence.py
not_again_ai/viz/__init__.py
not_again_ai/viz/barplots.py
not_again_ai/viz/distributions.py
not_again_ai/viz/scatterplot.py
not_again_ai/viz/time_series.py
not_again_ai/viz/utils.py
not_again_ai-0.21.0.dist-info/METADATA
not_again_ai-0.21.0.dist-info/WHEEL
not_again_ai-0.21.0.dist-info/licenses/LICENSE
not_again_ai-0.21.0.dist-info/RECORD
