Metadata-Version: 2.4
Name: not-again-ai
Version: 0.21.0
Summary: Designed to once and for all collect all the little things that come up over and over again in AI projects and put them in one place.
Project-URL: Homepage, https://github.com/DaveCoDev/not-again-ai
Project-URL: Documentation, https://davecodev.github.io/not-again-ai/
Project-URL: Repository, https://github.com/DaveCoDev/not-again-ai
Author-email: DaveCoDev <dave.co.dev@gmail.com>
License-Expression: MIT
License-File: LICENSE
Classifier: Development Status :: 3 - Alpha
Classifier: Intended Audience :: Developers
Classifier: Intended Audience :: Science/Research
Classifier: License :: OSI Approved :: MIT License
Classifier: Operating System :: OS Independent
Classifier: Programming Language :: Python
Classifier: Programming Language :: Python :: 3
Classifier: Programming Language :: Python :: 3.11
Classifier: Programming Language :: Python :: 3.12
Classifier: Typing :: Typed
Requires-Python: >=3.11
Requires-Dist: loguru<1.0,>=0.7
Requires-Dist: pydantic<3.0,>=2.11
Provides-Extra: data
Requires-Dist: crawl4ai<1.0,>=0.6; extra == 'data'
Requires-Dist: httpx<1.0,>=0.28; extra == 'data'
Requires-Dist: markitdown[pdf]==0.1.2; extra == 'data'
Provides-Extra: llm
Requires-Dist: anthropic<1.0,>=0.55; extra == 'llm'
Requires-Dist: azure-identity<2.0,>=1.23; extra == 'llm'
Requires-Dist: google-genai<2.0,>1.22; extra == 'llm'
Requires-Dist: ollama<1.0,>=0.5; extra == 'llm'
Requires-Dist: openai<2.0,>=1.93; extra == 'llm'
Requires-Dist: python-liquid<3.0,>=2.0; extra == 'llm'
Requires-Dist: tiktoken<1.0,>=0.9; extra == 'llm'
Provides-Extra: statistics
Requires-Dist: numpy<3.0,>=2.3; extra == 'statistics'
Requires-Dist: scikit-learn<2.0,>=1.7; extra == 'statistics'
Requires-Dist: scipy>=1.16; extra == 'statistics'
Provides-Extra: viz
Requires-Dist: numpy<3.0,>=2.3; extra == 'viz'
Requires-Dist: pandas<3.0,>=2.3; extra == 'viz'
Requires-Dist: seaborn<1.0,>=0.13; extra == 'viz'
